cz_path/__init__.py
cz_path/plugin.py
cz_path/py.typed
cz_path-0.0.4.dist-info/METADATA
cz_path-0.0.4.dist-info/WHEEL
cz_path-0.0.4.dist-info/entry_points.txt
cz_path-0.0.4.dist-info/licenses/LICENSE.txt
cz_path-0.0.4.dist-info/RECORD
