Metadata-Version: 2.4
Name: cz-path
Version: 0.0.4
Summary: Commitizen plugin that prefixes commit messages with the common path or prefix of staged files.
License-Expression: MIT
License-File: LICENSE.txt
Keywords: commitizen,commit messages,git,version control
Author: Andrew Udvare
Author-email: audvare@gmail.com
Requires-Python: >=3.10,<4.0
Classifier: Development Status :: 4 - Beta
Classifier: Intended Audience :: Developers
Classifier: Programming Language :: Python
Classifier: Programming Language :: Python :: 3.10
Classifier: Programming Language :: Python :: 3.11
Classifier: Programming Language :: Python :: 3.12
Classifier: Programming Language :: Python :: 3.13
Classifier: Programming Language :: Python :: 3.14
Classifier: Typing :: Typed
Requires-Dist: commitizen (>=4.10.0,<5.0.0)
Requires-Dist: gitpython (>=3.1.45,<4.0.0)
Requires-Dist: typing-extensions (>=4.15.0,<5.0.0)
Project-URL: Documentation, https://cz-path.readthedocs.org
Project-URL: Homepage, https://tatsh.github.io/cz-path/
Project-URL: Issues, https://github.com/Tatsh/cz-path/issues
Project-URL: Repository, https://github.com/Tatsh/cz-path
